gsdcli/gsdcli.py
gsdcli/servers.yaml
gsdcli-0.4.0.dist-info/entry_points.txt
gsdcli-0.4.0.dist-info/LICENSE
gsdcli-0.4.0.dist-info/WHEEL
gsdcli-0.4.0.dist-info/METADATA
gsdcli-0.4.0.dist-info/RECORD
