Metadata-Version: 2.1
Name: gsdcli
Version: 0.4.0
Summary: A cli for installing game servers
Author: egee-irl
Author-email: brian@egee.io
Requires-Python: >=3.6,<4.0
Classifier: Programming Language :: Python :: 3
Classifier: Programming Language :: Python :: 3.6
Classifier: Programming Language :: Python :: 3.7
Classifier: Programming Language :: Python :: 3.8
Classifier: Programming Language :: Python :: 3.9
Requires-Dist: Click (>=7.1.1,<8.0.0)
Requires-Dist: pyyaml (>=5.3.1,<6.0.0)
